setup.py
salmin_client.egg-info/PKG-INFO
salmin_client.egg-info/SOURCES.txt
salmin_client.egg-info/dependency_links.txt
salmin_client.egg-info/requires.txt
salmin_client.egg-info/top_level.txt
server/__init__.py
server/server.py
server/common/__init__.py
server/common/decor.py
server/common/dscrprt.py
server/common/errors.py
server/common/metacls.py
server/common/utils.py
server/common/uuid_profile.py
server/common/variables.py
server/log_profile/__init__.py
server/log_profile/logger_client.py
server/log_profile/logger_server.py
server/server/__init__.py
server/server/add_user.py
server/server/core.py
server/server/database.py
server/server/main_window.py
server/server/remove_user.py
server/server/setting_window.py
server/server/stat_window.py
server/unit_test/__init__.py
server/unit_test/test_client.py
server/unit_test/test_server.py