Metadata-Version: 2.1
Name: salmin-client
Version: 0.0.2
Summary: salmin_client
Home-page: UNKNOWN
Author: Oleg Salmin
Author-email: olegsalmin74@gmail.com
License: UNKNOWN
Platform: UNKNOWN
